updatable_zipfile/__init__.py
updatable_zipfile/_version.py
updatable_zipfile-0.1.2.dist-info/DESCRIPTION.rst
updatable_zipfile-0.1.2.dist-info/METADATA
updatable_zipfile-0.1.2.dist-info/RECORD
updatable_zipfile-0.1.2.dist-info/WHEEL
updatable_zipfile-0.1.2.dist-info/metadata.json
updatable_zipfile-0.1.2.dist-info/top_level.txt
zip_utils/__init__.py
zip_utils/_version.py
