Metadata-Version: 2.0
Name: updatable-zipfile
Version: 0.1.2
Summary: Updatable Zip File
Home-page: https://github.com/xoviat/updatable_zipfile
Author: Mars Galactic
Author-email: xoviat@users.noreply.github.com
License: GNU GENERAL PUBLIC LICENSE
